mockr.py
mockr-0.36.dist-info/METADATA
mockr-0.36.dist-info/RECORD
mockr-0.36.dist-info/WHEEL
mockr-0.36.dist-info/top_level.txt
