Metadata-Version: 2.1
Name: mockr
Version: 0.36
Summary: A Python library for prototyping MapReduce jobs
Home-page: https://github.com/sjtrny/mockr
Author: Stephen Tierney
Author-email: sjtrny@gmail.com
License: UNKNOWN
Keywords: mockr mapreduce map reduce education
Platform: UNKNOWN
Classifier: License :: OSI Approved :: MIT License
Requires-Python: >=3
Requires-Dist: pandas
